{
    "config": [
        {
            "admin": {
                "serverId": 1088294110747693168,
                "channelId": 1128720968760696863,
                "messageId": 1271832968641380392
            },
            "ticket": {
                "status": {
                    "1271834384575631394": {
                        "userId": 429458093265649686,
                        "status": "open",
                        "description": "jjjdjdjdi",
                        "messageId": 1271834390569160704
                    }
                }
            }
        },
        {
            "user": {
                "serverId": 1088294110747693168,
                "channelId": 1129264694977376317,
                "messageId": 1271833793547866244
            }
        },
        {
            "ticket": {
                "command": {
                    "serverId": 1088294110747693168,
                    "channelId": 1106166838586511421,
                    "messageId": 1271833883331002481
                },
                "status": {}
            }
        }
    ]
}